prettyetc/baseui/__init__.py
prettyetc/baseui/cmdargs.py
prettyetc/baseui/main.py
prettyetc/baseui/settings.py
prettyetc/baseui/utils.py
prettyetc/baseui/ui/__init__.py
prettyetc/baseui/ui/common.py
prettyetc/baseui/ui/field.py
prettyetc/baseui/ui/main.py
prettyetc/baseui/ui/settings.py
prettyetc/etccore/__init__.py
prettyetc/etccore/confmgr.py
prettyetc/etccore/logger.py
prettyetc/etccore/plugins.py
prettyetc/etccore/langlib/__init__.py
prettyetc/etccore/langlib/field.py
prettyetc/etccore/langlib/parsers.py
prettyetc/etccore/langlib/root.py
prettyetc/etccore/langlib/serializers.py
prettyetc/etccore/langs/__init__.py
prettyetc/etccore/langs/etclang.py
prettyetc/etccore/langs/inilang.py
prettyetc/etccore/langs/jsonlang.py
prettyetc/etccore/langs/xmllang.py
prettyetc/etccore/langs/yamllang.py
prettyetc/etccore/langs/etc/__init__.py
prettyetc/etccore/langs/etc/common.py
prettyetc/etccore/langs/etc/sep.py
prettyetc/etccore/langs/etc/space.py
prettyetc-0.4.0.dist-info/LICENSE
prettyetc-0.4.0.dist-info/METADATA
prettyetc-0.4.0.dist-info/WHEEL
prettyetc-0.4.0.dist-info/top_level.txt
prettyetc-0.4.0.dist-info/RECORD
