Metadata-Version: 2.1
Name: prettyetc
Version: 0.4.0
Summary: Core library of the prettyetc project
Home-page: https://gitlab.com/prettyetc/prettyetc
Author: trollodel
License: UNKNOWN
Project-URL: Bug Reports, https://gitlab.com/prettyetc/prettyetc/issues
Project-URL: Documentation, https://prettyetc.gitlab.io/prettyetc/
Project-URL: Source, https://gitlab.com/prettyetc/prettyetc
Keywords: configurations json ini etc qt
Platform: UNKNOWN
Classifier: Development Status :: 5 - Production/Stable
Classifier: License :: OSI Approved :: GNU General Public License v3 (GPLv3)
Classifier: Programming Language :: Python :: 3
Classifier: Programming Language :: Python :: 3.4
Classifier: Programming Language :: Python :: 3.5
Classifier: Programming Language :: Python :: 3.6
Classifier: Programming Language :: Python :: 3.7
Classifier: Programming Language :: Python :: 3.8
Classifier: Programming Language :: Python :: 3 :: Only
Classifier: Operating System :: OS Independent
Classifier: Topic :: Text Processing
Classifier: Topic :: Utilities
Classifier: Topic :: System :: Systems Administration
Classifier: Topic :: Documentation :: Sphinx
Classifier: Intended Audience :: Developers
Classifier: Intended Audience :: System Administrators
Requires-Python: >=3.4, <4
Provides-Extra: all
Requires-Dist: setuptools ; extra == 'all'
Requires-Dist: homebase ; extra == 'all'
Requires-Dist: lark-parser ; extra == 'all'
Requires-Dist: ruamel.yaml ; extra == 'all'
Provides-Extra: baseui
Requires-Dist: homebase ; extra == 'baseui'
Provides-Extra: etccore
Requires-Dist: setuptools ; extra == 'etccore'
Provides-Extra: plugins
Requires-Dist: lark-parser ; extra == 'plugins'
Requires-Dist: ruamel.yaml ; extra == 'plugins'
Provides-Extra: test
Requires-Dist: pytest ; extra == 'test'
Requires-Dist: hypothesis ; extra == 'test'
Requires-Dist: deepdiff ; extra == 'test'
Requires-Dist: lark-parser ; extra == 'test'
Requires-Dist: ruamel.yaml ; extra == 'test'
